Metadata-Version: 1.1
Name: bottle-errorsrest
Version: 0.0.3
Summary: ErrorsRest plugin for bottle
Home-page: https://github.com/agalera/bottle-errorsrest
Author: Alberto Galera Jimenez
Author-email: galerajimenez@gmail.com
License: GPL
Keywords: bottle_errorsrest
Platform: UNKNOWN
Classifier: Development Status :: 4 - Beta
Classifier: Topic :: Software Development :: Libraries :: Python Modules
Classifier: Intended Audience :: Developers
Classifier: License :: OSI Approved :: GNU General Public License (GPL)
Classifier: Natural Language :: English
Classifier: Programming Language :: Python :: 3
